my_funded_grpc_api/__init__.py
my_funded_grpc_api/trading_account/__init__.py
my_funded_grpc_api/trading_account/cash_balance_pb2.py
my_funded_grpc_api/trading_account/cash_balance_pb2_grpc.py
my_funded_grpc_api-1.0.0.dist-info/METADATA
my_funded_grpc_api-1.0.0.dist-info/WHEEL
my_funded_grpc_api-1.0.0.dist-info/top_level.txt
my_funded_grpc_api-1.0.0.dist-info/RECORD
