Metadata-Version: 2.1
Name: my-funded-grpc-api
Version: 1.0.0
Summary: gRPC API for My Funded trading
Home-page: https://github.com/MyFunded/my-funded-grpc-api
Author: Simeon Aleksov
Author-email: aleksov_s@outlook.com
Classifier: Programming Language :: Python :: 3
Classifier: License :: OSI Approved :: MIT License
Classifier: Operating System :: OS Independent
Requires-Python: >=3.7
Requires-Dist: grpcio>=1.32.0
Requires-Dist: protobuf>=3.14.0
